odoo_runbot/__init__.py
odoo_runbot/_odoo_internal.py
odoo_runbot/cli.py
odoo_runbot/runbot_config.py
odoo_runbot/runbot_env.py
odoo_runbot/runbot_init.py
odoo_runbot/runbot_init_branch_resolver.py
odoo_runbot/runbot_run.py
odoo_runbot/runbot_run_logging.py
odoo_runbot/runbot_run_test.py
odoo_runbot-1.8.0.dist-info/METADATA
odoo_runbot-1.8.0.dist-info/WHEEL
odoo_runbot-1.8.0.dist-info/entry_points.txt
odoo_runbot-1.8.0.dist-info/RECORD
