Metadata-Version: 2.4
Name: odoo-runbot
Version: 1.8.0
Summary: Main CLI to run test in GitLab CI
Author-email: Alexis PASQUIER <alexis.pasquier@mangono.fr>
Requires-Python: >=3.8
Requires-Dist: addons-installer>=3.9.0
Requires-Dist: coverage[toml]
Requires-Dist: environ-odoo-config>=0.6
Requires-Dist: python-gitlab>=4.13.0
Requires-Dist: tomli; python_version < '3.11'
Requires-Dist: typer
Requires-Dist: typing-extensions
Requires-Dist: unittest-xml-reporting
Provides-Extra: psycopg
Requires-Dist: psycopg2>=2.8.3; extra == 'psycopg'
